LICENSE
README.md
setup.py
LLMs/__init__.py
LLMs/api_utils.py
LLMs/llm_api.py
anab_ai_toolkit.egg-info/PKG-INFO
anab_ai_toolkit.egg-info/SOURCES.txt
anab_ai_toolkit.egg-info/dependency_links.txt
anab_ai_toolkit.egg-info/requires.txt
anab_ai_toolkit.egg-info/top_level.txt