Metadata-Version: 2.1
Name: anab-ai-toolkit
Version: 0.1.0.dev1
Summary: Useful functions for AI-related research.
Author: Ana Brassard
Author-email: brassard.ana@gmail.com
License-File: LICENSE
Requires-Dist: annotated-types==0.6.0
Requires-Dist: anyio==4.2.0
Requires-Dist: asttokens==2.4.1
Requires-Dist: cachetools==5.3.2
Requires-Dist: certifi==2024.2.2
Requires-Dist: charset-normalizer==3.3.2
Requires-Dist: click==8.1.7
Requires-Dist: contourpy==1.2.0
Requires-Dist: cycler==0.12.1
Requires-Dist: decorator==5.1.1
Requires-Dist: distro==1.9.0
Requires-Dist: executing==2.0.1
Requires-Dist: filelock==3.13.1
Requires-Dist: fonttools==4.47.2
Requires-Dist: fsspec==2024.2.0
Requires-Dist: google-ai-generativelanguage==0.4.0
Requires-Dist: google-api-core==2.16.2
Requires-Dist: google-auth==2.27.0
Requires-Dist: google-generativeai==0.3.2
Requires-Dist: googleapis-common-protos==1.62.0
Requires-Dist: grpcio==1.60.1
Requires-Dist: grpcio-status==1.60.1
Requires-Dist: h11==0.14.0
Requires-Dist: httpcore==1.0.2
Requires-Dist: httpx==0.26.0
Requires-Dist: huggingface-hub==0.20.3
Requires-Dist: idna==3.6
Requires-Dist: ipython==8.21.0
Requires-Dist: jedi==0.19.1
Requires-Dist: joblib==1.3.2
Requires-Dist: kiwisolver==1.4.5
Requires-Dist: matplotlib==3.8.2
Requires-Dist: matplotlib-inline==0.1.6
Requires-Dist: nltk==3.8.1
Requires-Dist: numpy==1.26.4
Requires-Dist: openai==1.11.1
Requires-Dist: packaging==23.2
Requires-Dist: pandas==2.2.0
Requires-Dist: parso==0.8.3
Requires-Dist: pexpect==4.9.0
Requires-Dist: pillow==10.2.0
Requires-Dist: prompt-toolkit==3.0.43
Requires-Dist: proto-plus==1.23.0
Requires-Dist: protobuf==4.25.2
Requires-Dist: ptyprocess==0.7.0
Requires-Dist: pure-eval==0.2.2
Requires-Dist: pyasn1==0.5.1
Requires-Dist: pyasn1-modules==0.3.0
Requires-Dist: pydantic==2.6.1
Requires-Dist: pydantic_core==2.16.2
Requires-Dist: Pygments==2.17.2
Requires-Dist: pyparsing==3.1.1
Requires-Dist: python-dateutil==2.8.2
Requires-Dist: pytz==2024.1
Requires-Dist: PyYAML==6.0.1
Requires-Dist: regex==2023.12.25
Requires-Dist: requests==2.31.0
Requires-Dist: rsa==4.9
Requires-Dist: safetensors==0.4.2
Requires-Dist: seaborn==0.13.2
Requires-Dist: setuptools==68.2.2
Requires-Dist: six==1.16.0
Requires-Dist: sniffio==1.3.0
Requires-Dist: stack-data==0.6.3
Requires-Dist: tokenizers==0.15.1
Requires-Dist: tqdm==4.66.1
Requires-Dist: traitlets==5.14.1
Requires-Dist: transformers==4.37.2
Requires-Dist: typing_extensions==4.9.0
Requires-Dist: tzdata==2023.4
Requires-Dist: urllib3==2.2.0
Requires-Dist: wcwidth==0.2.13
Requires-Dist: wheel==0.41.2
